node.ext.ldap-1.2-py3.9-nspkg.pth
node/ext/ldap/__init__.py
node/ext/ldap/_node.py
node/ext/ldap/base.py
node/ext/ldap/cache.py
node/ext/ldap/events.py
node/ext/ldap/filter.py
node/ext/ldap/interfaces.py
node/ext/ldap/main.py
node/ext/ldap/properties.py
node/ext/ldap/schema.py
node/ext/ldap/scope.py
node/ext/ldap/session.py
node/ext/ldap/testing/__init__.py
node/ext/ldap/testing/data/binary.jpg
node/ext/ldap/testing/ldifs/base.ldif
node/ext/ldap/testing/ldifs/data.ldif
node/ext/ldap/testing/ldifs/genPosixGroups.py
node/ext/ldap/testing/ldifs/genSambaUsers.py
node/ext/ldap/testing/ldifs/gengroupOfNames.py
node/ext/ldap/testing/ldifs/genusers.py
node/ext/ldap/testing/ldifs/groupOfNames.ldif
node/ext/ldap/testing/ldifs/groupOfNames_1000_1000.ldif
node/ext/ldap/testing/ldifs/groupOfNames_100_100.ldif
node/ext/ldap/testing/ldifs/groupOfNames_10_10.ldif
node/ext/ldap/testing/ldifs/groupOfNames_300_300.ldif
node/ext/ldap/testing/ldifs/groupOfNames_700_700.ldif
node/ext/ldap/testing/ldifs/posixGroups.ldif
node/ext/ldap/testing/ldifs/posixGroups_10_10.ldif
node/ext/ldap/testing/ldifs/principals.ldif
node/ext/ldap/testing/ldifs/sambaUsers.ldif
node/ext/ldap/testing/ldifs/users1000.ldif
node/ext/ldap/testing/ldifs/users2000.ldif
node/ext/ldap/testing/ldifs/users300.ldif
node/ext/ldap/testing/ldifs/users700.ldif
node/ext/ldap/testing/schema/README
node/ext/ldap/testing/schema/ad.dummy.schema
node/ext/ldap/testing/schema/collective.schema
node/ext/ldap/testing/schema/corba.schema
node/ext/ldap/testing/schema/core.ldif
node/ext/ldap/testing/schema/core.schema
node/ext/ldap/testing/schema/cosine.ldif
node/ext/ldap/testing/schema/cosine.schema
node/ext/ldap/testing/schema/duaconf.schema
node/ext/ldap/testing/schema/dyngroup.schema
node/ext/ldap/testing/schema/inetorgperson.ldif
node/ext/ldap/testing/schema/inetorgperson.schema
node/ext/ldap/testing/schema/java.schema
node/ext/ldap/testing/schema/misc.schema
node/ext/ldap/testing/schema/nis.ldif
node.ext.ldap-1.2.dist-info/LICENSE.rst
node.ext.ldap-1.2.dist-info/METADATA
node.ext.ldap-1.2.dist-info/WHEEL
node.ext.ldap-1.2.dist-info/entry_points.txt
node.ext.ldap-1.2.dist-info/namespace_packages.txt
node.ext.ldap-1.2.dist-info/top_level.txt
node.ext.ldap-1.2.dist-info/RECORD
