Metadata-Version: 2.1
Name: node.ext.ldap
Version: 1.2
Summary: LDAP/AD convenience with Node-trees based on python-ldap
Home-page: https://github.com/conestack/node.ext.ldap
Author: Node Contributors
Author-email: dev@conestack.org
License: Simplified BSD
Keywords: ldap authentication node tree access users groups
Platform: UNKNOWN
Classifier: Development Status :: 5 - Production/Stable
Classifier: License :: OSI Approved :: BSD License
Classifier: Intended Audience :: Developers
Classifier: Operating System :: OS Independent
Classifier: Topic :: Software Development
Classifier: Topic :: System :: Systems Administration :: Authentication/Directory :: LDAP
Classifier: Programming Language :: Python
Classifier: Programming Language :: Python :: 2.7
Classifier: Programming Language :: Python :: 3.7
Classifier: Programming Language :: Python :: 3.8
Classifier: Programming Language :: Python :: 3.9
Classifier: Programming Language :: Python :: 3.10
Requires-Dist: bda.cache
Requires-Dist: node (>=1.1)
Requires-Dist: node.ext.ugm (>=1.0)
Requires-Dist: passlib
Requires-Dist: python-ldap (>=2.4.14)
Requires-Dist: setuptools
Requires-Dist: argparse ; python_version < "3.2"
Provides-Extra: test
Requires-Dist: coverage ; extra == 'test'
Requires-Dist: plone.testing ; extra == 'test'
Requires-Dist: zope.configuration ; extra == 'test'
Requires-Dist: zope.testing ; extra == 'test'
Requires-Dist: zope.testrunner ; extra == 'test'
